setup.cfg
setup.py
sheetDB/__init__.py
sheetDB/constants.py
sheetDB/credentials.py
sheetDB/database.py
sheetDB/errors.py
sheetDB/functions.py
sheetDB/sheet.py
sheetDB/table.py
sheetDB/worksheet.py
sheetDB.egg-info/PKG-INFO
sheetDB.egg-info/SOURCES.txt
sheetDB.egg-info/dependency_links.txt
sheetDB.egg-info/requires.txt
sheetDB.egg-info/top_level.txt