Metadata-Version: 1.1
Name: sheetDB
Version: 0.1.11
Summary: a library to use Google Sheets as a backend
Home-page: https://github.com/knyte/sheetDB
Author: knyte
Author-email: galactaknyte@gmail.com
License: MIT
Download-URL: https://github.com/knyte/sheetDB/tarball/0.1.11
Keywords: Google Sheets,spreadsheets,gspread
Platform: UNKNOWN
